odoo/addons/ssi_fleet_work_order/README.rst
odoo/addons/ssi_fleet_work_order/__init__.py
odoo/addons/ssi_fleet_work_order/__manifest__.py
odoo/addons/ssi_fleet_work_order/data/approval_template_data.xml
odoo/addons/ssi_fleet_work_order/data/ir_sequence_data.xml
odoo/addons/ssi_fleet_work_order/data/policy_template_data.xml
odoo/addons/ssi_fleet_work_order/data/sequence_template_data.xml
odoo/addons/ssi_fleet_work_order/models/__init__.py
odoo/addons/ssi_fleet_work_order/models/fleet_vehicle.py
odoo/addons/ssi_fleet_work_order/models/fleet_work_order.py
odoo/addons/ssi_fleet_work_order/models/fleet_work_order_route.py
odoo/addons/ssi_fleet_work_order/models/fleet_work_order_route_template.py
odoo/addons/ssi_fleet_work_order/models/fleet_work_order_route_template_category.py
odoo/addons/ssi_fleet_work_order/models/fleet_work_order_route_template_route.py
odoo/addons/ssi_fleet_work_order/models/fleet_work_order_type.py
odoo/addons/ssi_fleet_work_order/reports/__init__.py
odoo/addons/ssi_fleet_work_order/reports/fleet_work_order_analysis.py
odoo/addons/ssi_fleet_work_order/reports/fleet_work_order_analysis.xml
odoo/addons/ssi_fleet_work_order/security/ir.model.access.csv
odoo/addons/ssi_fleet_work_order/security/ir_module_category_data.xml
odoo/addons/ssi_fleet_work_order/security/ir_rule_data.xml
odoo/addons/ssi_fleet_work_order/security/res_group_data.xml
odoo/addons/ssi_fleet_work_order/static/description/icon.png
odoo/addons/ssi_fleet_work_order/views/fleet_vehicle_views.xml
odoo/addons/ssi_fleet_work_order/views/fleet_work_order_route_template_category_views.xml
odoo/addons/ssi_fleet_work_order/views/fleet_work_order_route_template_views.xml
odoo/addons/ssi_fleet_work_order/views/fleet_work_order_type_views.xml
odoo/addons/ssi_fleet_work_order/views/fleet_work_order_views.xml
odoo14_addon_ssi_fleet_work_order-14.0.3.0.0.dist-info/METADATA
odoo14_addon_ssi_fleet_work_order-14.0.3.0.0.dist-info/WHEEL
odoo14_addon_ssi_fleet_work_order-14.0.3.0.0.dist-info/top_level.txt
odoo14_addon_ssi_fleet_work_order-14.0.3.0.0.dist-info/RECORD
